Metadata-Version: 2.1
Name: logma
Version: 0.3.0
Summary: defaults for structlog
Home-page: https://github.com/peakiq/logma
Author: peakiq
License: UNKNOWN
Platform: UNKNOWN
Classifier: Programming Language :: Python :: 3
Classifier: Operating System :: OS Independent
Provides-Extra: tests
